{"fsgt.org":[1,12,3],"fsguestsfirst.com":[1],"fshare.vn":[1,12,5],"fshield.net":[12],"fshost.me":[1,12,5],"fsisac.com":[1,12],"fsitaliane.it":[12],"fsm-team.de":[1,3],"fsmb.org":[1,12,4],"fsnb.com":[1,2],"fsoft.com.vn":[12],"fsonline.com":[1],"fsource.org":[1,2],"fspilotshop.com":[1,9],"fspsstore.com":[1,9],"fsr-california.com":[1,12],"fsrealwx.net":[7],"fsreloading.com":[9],"fsresidential.com":[1,12],"fss.com":[1,9],"fssai.gov.in":[1,12],"fssdev.com":[1,5],"fssgames.com":[1],"fssnet.co.in":[12],"fstop.fm":[1],"fstopgear.com":[1,9],"fstoppers.com":[1,12,3],"fsts.ac.ma":[1,12],"fsu.edu":[12],"fsvsecurecard.com":[12],"fsw.edu":[12],"fsweb.no":[1,12],"fsx-france.com":[1,12],"fsxcc.com":[1,12],"fsxinsider.com":[1],"fszek.hu":[1,12],"ft.com":[1,12,7],"ft86club.com":[3,12],"ft86speedfactory.com":[9],"ftabeta.com":[5,10],"ftaconcept.com":[1,12,10],"ftadviser.com":[1],"ftaprofessionals.tv":[5],"ftax.co.uk":[1],"ftazeta.com":[5,10],"ftb.com":[1,2],"ftbservers.com":[3,3],"ftc.gov":[1,12],"ftchinese.com":[1,12],"ftd.ca":[1,9],"ftd.com":[1,9],"ftd.com.br":[1,12],"ftd.de":[1],"ftdfloristsonline.com":[1],"ftdworld.net":[12],"ftfansub.net":[12],"ftjfundchoice.com":[1],"ftjfundchoice.net":[1],"ftlgame.com":[12],"ftm.nl":[1,12],"ftmodding.fr":[12],"ftop.ru":[12],"ftplive.com":[12],"ftploy.com":[1,5],"ftportfolios.com":[1,2],"ftpsllc.com":[1],"ftpstream.com":[1,5],"ftptest.net":[1,5],"ftptoday.com":[1,5],"ftr.com":[1],"ftrackapp.com":[12],"ftregistration.com":[1,9],"ftrsecure.com":[1,5],"ftvgirls.com":[12],"ftvmembers.com":[12],"ftw.in":[1],"ftwccu.org":[1],"ftwilliam.com":[1],"fu-berlin.de":[12],"fubar.com":[1,12],"fubiz.net":[1],"fubles.com":[1,3],"fubo.tv":[7,3],"fubra.com":[1],"fuchstreff.de":[1,12,3],"fuck-buddies.com":[12],"fuck-girls-today.com":[12],"fuckbook.com":[10],"fuckbook.org":[10],"fuckbook.tv":[10],"fuckbook.xxx":[10],"fuckbookafricaine.com":[12,1],"fuckbookhookups.com":[10],"fuckbooknet.net":[10],"fuckbookromania.com":[12,1],"fuckbooksite.com":[10],"fuckbuddy.co.uk":[12,1],"fuckcombustion.com":[12,10],"fuckdate.com":[10]}