{"converzly.net":[12],"convex.ru":[12],"convey.de":[1],"conviasa.aero":[1,12,11],"convio.net":[1,12],"convirza.com":[1],"conviva.com":[1],"convivea.com":[1,5],"convo.com":[1,12],"convore.com":[12],"conxport.com":[1],"conyac.cc":[1,12],"coobis.com":[1],"coobiz.it":[1,12,9],"coocox.org":[1,12],"cook-and-chef.com":[1,9],"cook-and-go.com":[1,12,3],"cook-shop.fr":[1,3,9],"cookandco.nl":[1,3,9],"cookandcoffee.fr":[1,3],"cookaround.com":[1,3],"cookcountyboardofreview.com":[12],"cookcountyclerk.com":[1,12],"cookcountygenealogy.com":[1,12],"cookcountyil.gov":[1,12],"cookcountytreasurer.com":[1,12],"cookcountyuscourts.com":[12],"cookeatshare.com":[1,3],"cookfood.net":[1,3],"cookidoo.de":[1,3],"cookidoo.fr":[1,3],"cookie-script.com":[1],"cookiedelivery.com":[1],"cookiehosting.net":[1,5],"cookiesbydesign.com":[1,9],"cookieskids.com":[9],"cookiesmakeup.com":[1],"cooking-chef.fr":[1,3],"cooking.com":[12],"cookingchanneltv.com":[1,3],"cookingclub.com":[3],"cookinglight.com":[3],"cookinglightdiet.com":[1,3],"cookingschoolsofamerica.com":[12],"cookingwithnonna.com":[1,3],"cookishop.com":[1,3,9],"cookkeepbook.com":[1,3],"cookloveshare.nl":[1,12],"cookman.edu":[12],"cookmore.com":[1,12],"cookomix.com":[1,3],"cookpad.com":[1,3],"cookpolitical.com":[1,12],"cookscountry.com":[1,3],"cooksillustrated.com":[1],"cooksmarts.com":[1,3],"cookson-clal.com":[9],"cooksongold.com":[1,9],"cookstr.com":[1,3],"cookwithcampbells.ca":[3],"cool-traffic.com":[12],"cool18.com":[1,12],"coolaler.com":[12],"coolapk.com":[1,12,5],"coolaroousa.com":[9],"coolaustralia.org":[1,12],"coolbet.com":[3],"coolblue.be":[12],"coolblue.nl":[9],"coolcadeau.fr":[1],"coolcalc.com":[1,12],"coolcamping.co.uk":[1],"coolcat-casino.com":[3,3],"coolcat.nl":[9],"coolcat.org":[12],"coolcathits.com":[1],"coolcompany.com":[1],"coolcomponents.co.uk":[9],"coolenjoy.net":[1,5,9],"coolermaster.com":[1,9],"cooley.com":[1,12],"coolframes.com":[9],"coolhandle.com":[1,5],"coolibar.com":[9],"coolicool.com":[9],"coolidge.org":[1,12,3],"coolinarika.com":[1,12],"cooliris.com":[1],"coolkit.cc":[12],"coolmath-games.com":[12,3],"coolmilk.com":[1,12],"coolminiornot.com":[3],"coolmod.com":[5,9],"coolnetalberta.com":[1,12],"coolors.co":[1,5],"coolpadforums.com":[1,3],"coolpage.biz":[1,5],"coolpc.com.tw":[12],"coolphotos.de":[1,12]}