{"regularlabs.com":[1,5],"regulatedconsultants.com":[1],"regulations.gov":[12],"regulatoryu.com":[1,12],"regus.com":[1],"rehabbingo.com":[3,3],"rehabvaluator.com":[1],"rehnonline.com":[1],"rehost.to":[12],"rei.com":[9],"rei.jobs":[1,12],"reibert.info":[1,3,9],"reiblackbook.com":[1],"reichelt.at":[1,9],"reichelt.com":[1,9],"reichelt.de":[1,9],"reico-vital.com":[1,12,9],"reidreviews.com":[1,12],"reidsystems.com":[12],"reif6.com":[12],"reife-milfs.de":[12],"reifedates.com":[10],"reifefrauen.com":[12,9],"reifen.com":[1,9],"reifenchampion.de":[1,9],"reifendirekt.at":[9,12],"reifendirekt.ch":[1,9,12],"reifendirekt.de":[9,12],"reifendiscount.de":[1,9,12],"reifengundlach.de":[1,9],"reifenleader.de":[9,12],"reifensuche.com":[12,9],"reiferflirtclub.com":[10],"reiferflirtgesucht.com":[10],"reifesexflirts.com":[10],"reiformslive.com.au":[1],"reignofblood.net":[3,3],"reikan.co.uk":[1,5],"reikiwebstore.com":[1,9],"reimageplus.com":[1,5],"reimastercard.com":[12],"reimatcher.com":[1],"reimo.com":[1,9],"reimsmetropole.fr":[1,12],"reiner-sct.com":[1],"reinhardt.edu":[12],"reinigungsberater.de":[1,9],"reinmls.com":[1,12],"reinz.co.nz":[1],"reiquickcashsystem.com":[12],"reis.com":[1],"reisebank.de":[1,9],"reisen.de":[11],"reisenthel.com":[9],"reislogger.nl":[1,12],"reisource.com":[12],"reiss.com":[9],"reitmans.com":[9],"reiv.com.au":[1,12],"reiwa.com.au":[1,8],"reiwise.com":[1],"rejis.org":[1],"rejsekort.dk":[1,9],"rejuvenation.com":[9],"reka.ch":[1,12],"rekanet.ch":[1],"rekentuin.nl":[1,12],"rekini.lv":[1],"reklama5.mk":[12],"reklamni-auditor.cz":[1],"reklamnymail.sk":[1,5],"rekordbox.com":[1,3],"rekrute.com":[1,6],"rekruter.de":[1,6],"rekryteringsmyndigheten.se":[1,12],"rekrytointi.com":[1,6],"relais-host.com":[1,12],"relaischateaux.com":[1,12,11],"relaiscolis.com":[1],"relakks.com":[1],"relapse.com":[12],"related.com":[1,11],"relateiq.com":[1],"relatieplanet.nl":[10],"relation-usagers.fr":[12],"relativefinder.org":[1,12],"relaxbanking.it":[12],"relaxcube.com":[1,12,3],"relay.com":[1,12,9],"relayfoods.com":[1,12],"relayhealth.ca":[1,4],"relayhealth.com":[1],"relayit.com":[12],"relayit.net":[1,12,5],"relayrides.com":[1],"relayshopusa.com":[1,9],"relaythat.com":[1],"relaytxt.io":[1,12],"relayware.com":[1]}