{"agario.biz":[3],"agario.mobi":[3],"agariohub.net":[1],"agariomods.com":[1,12],"agarprivateserver.com":[1,3,5],"agarserv.com":[1,5],"agarvipbots.com":[1],"agarwalinnosoft.com":[1,12,5],"agarymathematics.net":[3],"agarz.com":[1,3,5],"agate-france.com":[12,7],"agate.ch":[1,12],"agatha.fr":[1,9],"agava.ru":[1,5],"agb.de":[1],"agbar.net":[12],"agbcode.nl":[1,12],"agc.org":[1,12],"agcareers.com":[1,6],"agcm.it":[1,12],"agcocorp.com":[1],"agd.org":[1,12],"age-of-aincrad.com":[1],"agea.com":[1,2],"agea.com.ar":[12],"ageas.fr":[1],"ageas.pt":[1],"agecommunity.com":[1,12,3],"agedwards.com":[1,2],"agefi.fr":[1,2,12],"agefiactifs.com":[1,12],"agefiph.fr":[1,12],"agefos-pme.com":[1,12],"agefotostock.com":[1,10],"agehotel.info":[1,12],"agehotel.me":[1],"agehotel.org":[1,12],"agel.com":[1,12],"agem.sk":[9],"agematch.com":[10],"agemni.com":[1],"agenaastro.com":[9],"agenas.it":[1,12,4],"agence-api.fr":[1,12],"agence-presse.net":[1],"agencebio.org":[1,12],"agencerecherche.fr":[12],"agenceweb.com":[1,5],"agencyaccess.com":[1],"agencyanalytics.com":[1],"agencybloc.com":[1],"agencyequity.com":[1,2],"agencyexpress3.org":[1],"agencymatrix.com":[1],"agencyprosoftware.com":[1],"agencyspotter.com":[1],"agenda-discount.fr":[1,3,9],"agenda-kunden.de":[1,5],"agenda-lgo.de":[12],"agenda-loto.net":[12],"agenda.co.jp":[1],"agendaculturel.fr":[12,3],"agendashow.com":[1,12],"agendeumaconsulta.com.br":[1],"agendio.com":[1,9],"agendor.com.br":[1],"agendrix.com":[1],"agent-co.fr":[1],"agent-servicing.com":[12],"agentaccount.com":[12],"agentachieve.com":[1],"agentboxcrm.com.au":[1],"agentconnect.biz":[12],"agentdesks.com":[10,11],"agentexchange.com":[1],"agentexperience.com":[1],"agentexpressway.com":[1],"agentgrid.net":[1],"agentinfocenter.com":[1],"agentinside.com":[1],"agentmachine.com":[8],"agentmarketing.com":[1],"agentmaxonline.com":[12],"agentnetinfo.com":[1],"agentology.com":[1],"agentpipeline.com":[1],"agentpro247.com":[1],"agentprovocateur.com":[12,9],"agentsearch.jp":[1,6],"agentsolo.com":[1],"agentstudio.com":[1],"agenttrax.com":[1,5],"agentuniverse.com":[1],"agentur-filmgesichter.de":[1,12,3],"agentviewcigna.com":[1,2],"agentxcelerator.com":[12],"agenziabpb.it":[1,12],"agenziadogane.it":[12],"agenziadoganemonopoli.gov.it":[1,12]}