{"giffgaff.com":[1],"gifi.fr":[1,9],"gifs.com":[10],"gifsoup.com":[12],"giftango.com":[1,9],"giftbit.co.in":[1],"giftcard.ir":[1,9],"giftcardandloyalty.com":[1],"giftcardbin.com":[9],"giftcardgranny.com":[1,9],"giftcardlab.com":[1,9],"giftcardmall.com":[9],"giftcardrescue.com":[1],"giftcards.com":[1,9],"giftcards.com.au":[1,9],"giftcardspread.com":[9],"giftcardstore.ca":[9],"giftcardzen.com":[1,9],"giftcertificates.com":[1],"giftedandtalented.com":[12],"gifthulk.com":[1],"gifthunterclub.com":[1],"giftissue.com":[1,9],"giftkoeder-radar.com":[1,12],"giftly.com":[1,9],"giftnetonline.com":[1],"giftnix.com":[9],"gifto.io":[1,12],"giftobit.com":[1,12],"giftoff.com":[1,9],"giftpax.com.au":[1,9],"giftregistry360.com":[12],"giftrete.com":[9],"giftrocker.com":[1],"giftrocket.com":[1,9],"gifts.com":[1,9],"giftsandcare.com":[9],"giftsforyounow.com":[9],"giftsintl-us.com":[9],"giftsnideas.com":[1,9],"giftstation.co.nz":[1,9],"giftster.com":[1,9],"gifttool.com":[1],"gifttree.com":[12,9],"gifyo.com":[12],"gifzign.com":[10],"giga-byte.co.uk":[5],"giga-rapid.com":[1,5],"giga-watt.com":[1,5],"giga.cube":[12],"giga.de":[3,5,7],"giga.gg":[1,5],"gigaalert.com":[1],"gigablue-support.org":[12,3],"gigabyte.com":[1,5],"gigabyte.com.tw":[1,5,9],"gigabyte.fr":[1,5],"gigaflat.com":[12],"gigaflat.net":[12],"gigagolf.com":[1,9],"gigahash.org":[12],"gigahost.dk":[1,5],"gigajob.com":[1,6],"giganews.com":[1,5],"gigantic.com":[1,12,3],"giganticsolos.com":[1,9],"gigantti.fi":[1,9],"gigaom.com":[1,12,5],"gigapan.com":[1],"gigaparts.com":[9],"gigapeta.com":[12],"gigarank.net":[1,5],"gigarocket.net":[1,5],"gigas.com":[1,5],"gigaset-elements.com":[1],"gigaset.com":[1,5],"gigasize.com":[1,5,10],"gigasnutrition.com":[3,9],"gigasports.com":[1],"gigatorrents.ws":[1,12],"gigatribe.com":[1,5,10],"gigatribehub.com":[1,10],"gigatronshop.com":[9],"gigats.com":[1],"gigaviews.com":[3],"gigawatt.sg":[1,9],"gigbucks.com":[1],"gigbuilder.com":[1],"gigfa.com":[1,5],"giggle.com":[1,9],"gigmasters.com":[1,3],"gigmit.com":[1,3],"gigmor.com":[12],"gigroup.com":[1,12],"gigroup.it":[1,6],"gigsalad.com":[1],"gigsandtours.com":[1],"gigsky.com":[12,11],"gigspot.com":[1]}