{"lancaster.ac.uk":[12],"lancaster.com":[12],"lancasterarchery.com":[9,12],"lancasterlibraries.org":[1,12],"lancasteronline.com":[1,12,7],"lancement-e.com":[1,12],"lancenet.com.br":[3],"lancers.jp":[1,12],"lancom-systems.com":[1,5],"lancom-systems.de":[1,5],"lancome-usa.com":[9],"lancome.ca":[9],"lancome.fr":[9],"lancs.ac.uk":[12],"lancsngfl.ac.uk":[12],"land-der-traeume.de":[1,12],"landairsea.com":[1,9],"landandfarm.com":[8,9],"landashop.com":[1,9],"landbank.com.tw":[1,2],"landbelleasy-shop.de":[1],"landbot.io":[1,12],"landbote.ch":[1,12,7],"landbw.de":[12],"landc.co.uk":[1],"landchecker.com.au":[1],"landefeld.de":[1,9],"lander.edu":[12],"landerapp.com":[1,5],"landesk.com":[1],"landestheater-linz.at":[1,12,3],"landex.com":[1],"landg.com":[1],"landing.jobs":[1,5,6],"landingi.com":[1],"landingpagemonkey.com":[1],"landlordaxainsurance.com":[12],"landlordhub.com":[12],"landlordregistrationscotland.gov.uk":[1],"landlords.org.uk":[1,12],"landlordsofamerica.com":[12],"landlordstation.com":[1,12],"landlordtap.com":[1],"landlordvision.co.uk":[1],"landlordzone.co.uk":[1,12],"landman.org":[12],"landmarkbank.com":[1,2],"landmarkbingo.co.uk":[3,3],"landmarkcinemas.com":[3],"landmarkcu.com":[1,2],"landmarkcuonline.com":[1,2],"landmarketingmailer.com":[1],"landmarkgroup.com":[1],"landmarkhw.com":[1],"landmarknetwork.com":[1],"landmarkthegame.com":[1],"landmarktrust.org.uk":[1,12],"landmarkworldwide.com":[1,12],"landnsea.net":[1,5],"landofcoder.com":[1,9],"landofnod.com":[9],"landolakes.com":[12],"landolakesinc.com":[1,12],"landr.com":[1],"landregistry.gov.uk":[1,12],"landrover.com":[12],"landroverexcellence.com":[1,12],"landrovernet.com":[12,3,12],"landrysselect.com":[1,12],"landsbankinn.is":[2],"landscapelightingworld.com":[1,9],"landscapephotographymagazine.com":[1,12,3],"landscapepro.pics":[1],"landsend.co.jp":[9],"landsend.co.uk":[9],"landsend.com":[9],"landsend.de":[9],"landsofamerica.com":[8],"landsoflords.com":[1,3],"landsoftexas.com":[1,8],"landstaronline.com":[1],"landstede.net":[1],"landstedegroep.net":[1],"landvoice.com":[1],"landwars.com.br":[1,3],"landwatch.com":[1,8],"landwehr-hosting.de":[1,5],"landwirt.com":[1,12],"landyschemist.com":[4,9],"landyzone.co.uk":[1,12],"lane.edu":[12],"lanebryant.com":[9],"lanecc.edu":[12],"lanef.com":[1,12],"lanepl.org":[1,12],"lanes.io":[12],"lanet.me":[12],"lanet.ua":[1,5],"laneveraroja.com":[1,3]}