{"gameduell.co.uk":[3],"gameduell.com":[3],"gameduell.de":[3],"gameduell.fr":[3],"gameduell.nl":[3],"gameex.info":[1,5,10],"gameexpres.sk":[3,9],"gamefa.com":[3,3],"gameface.photos":[1,12,3],"gamefaceleague.com":[1],"gamefanshop.com":[12],"gamefaqs.com":[3],"gamefaucet.com":[1,3],"gamefazt.com":[3],"gamefiles.de":[3],"gamefilm-consultants.com":[12],"gameflare.com":[12,3,3],"gameflier.com":[12],"gameflip.com":[3,9],"gamefly.com":[3,7],"gamefoo.net":[1,3],"gamefools.com":[3],"gameforge.com":[12],"gamefound.com":[1],"gamefront.com":[1,3],"gamefroot.com":[1,12],"gamefuse.com":[1,3],"gamegear.be":[1,9],"gamegolf.com":[1,3],"gamegtx.com":[1,3,10],"gameguardian.net":[1,12,5],"gameguyz.com":[12],"gamehacking.org":[12,3,5],"gamehag.com":[1,3,3],"gamehero.com":[12],"gameho.net":[12],"gameholds.com":[9],"gamehosting.it":[1,12,5],"gamehouse.com":[3],"gameiki.com":[3,5],"gameinformer-activate.com":[1],"gameinformer.com":[3],"gameinstitute.com":[1,12],"gamejolt.com":[3],"gamek.vn":[3,3],"gamekey.com.br":[9],"gamekeybox.com":[3,9],"gamekeys.biz":[12],"gamekeys4all.com":[9],"gamekeys4u.net":[12],"gamekeyz.net":[1],"gamekiller.net":[1,5,10],"gameking.com":[12],"gamekings.tv":[3],"gamekiss.com":[12],"gamekit.com":[3],"gameknot.com":[12,3],"gamekult.com":[3,3,7],"gameladen.com":[3,9],"gameliebe.com":[3,9],"gamelink.com":[12],"gameloft.com":[1,3],"gameloft.fr":[1],"gameloft.org":[1],"gameloot.gift":[3],"gamelootnetwork.com":[12],"gamelumi.com":[1,3,3],"gamemachine.io":[1],"gamemafia.pro":[1,3],"gamemakerserver.com":[1,5],"gamemania.be":[3],"gamemania.nl":[3],"gamemaps.com":[12,3,3],"gameme.com":[12,3],"gamemodding.net":[3,10],"gamemodels.ru":[12],"gamenet.ru":[3,3],"gamengame.com":[3,3],"gameofbombs.com":[12],"gameofficials.net":[3],"gameofwartune.com":[1,12],"gameone.com":[12],"gameontabletop.com":[12],"gameoverth.com":[3,3,10],"gamepark.cz":[3,3],"gamepc.nl":[1,3,9],"gamepedia.com":[12,3,3],"gameplanet.com":[3],"gameplorer.de":[3,5,9],"gamepoint.com":[1,3,3],"gamepoint.de":[1,3],"gamepopz.com":[1,3],"gamepot.co.jp":[1,5],"gamepower7.com":[1,12,3],"gamepress.gg":[12],"gamepressure.com":[3,3],"gamepro.de":[3,7],"gamer-district.org":[12],"gamer-mods.ru":[12,3,3]}