{"musica.com":[3],"musica.ly":[12],"musicaficionado.com":[1],"musical.ly":[12],"musicalion.com":[1,12],"musicalley.com":[12],"musically.com":[1,12],"musicallyvideos.com":[3,5],"musicaneo.com":[1,12],"musicarts.com":[9],"musicasregistradas.com":[1,12],"musicbed.com":[1,12],"musicbot4you.net":[1,5],"musicbrainz.org":[1,12,5],"musicchoice.com":[3,3],"musicclout.com":[1,12],"musicdevelopmentprogram.org":[1,12],"musicdirect.com":[9],"musicdispatch.com":[12,3,9],"musicelster.net":[12],"musicflac.net":[3,3],"musicforall.org":[1,12],"musicfox.com":[1,12,3],"musicgateway.net":[1],"musicgear-news.com":[12],"musicglue.com":[1],"musicgoround.com":[1,9],"musicheaven.gr":[12,3,3],"musiciansfriend.com":[9],"musiciansunion.org.uk":[1,12],"musiciens-dans-ta-ville.com":[12],"musicinfosystems.com":[12],"musicisum.net":[1,12],"musick8.com":[1,12,3],"musiclab.com":[1,12,3],"musicload.de":[3,9],"musicmagpie.co.uk":[1,9],"musicmatch.com":[3,7],"musicme.com":[3,3],"musicmonster.fm":[3],"musicmp3.ru":[12],"musicnotes.com":[12,3,3],"musicoin.org":[1],"musicool.cn":[1,12,3],"musicovery.com":[1,12],"musicplayer.com":[12],"musicplayon.com":[3,3],"musicproinsurance.com":[1],"musicradio.com":[1],"musicraiser.com":[1],"musicreports.com":[1,5],"musicroom.com":[12,3,9],"musicroom.fr":[1,12,9],"musics247.com":[1],"musicshake.com":[3,3],"musicstack.com":[2,12,9],"musicstore.com":[1,9],"musicstore.de":[1,9],"musicsubmit.com":[1,3,3],"musicteachers.co.uk":[1,12],"musicteachershelper.com":[1,12],"musictoday.com":[1],"musictogether.com":[1,12],"musictrace.de":[1,12],"musicweek.com":[1,3],"musicworldbrilon.de":[1,9],"musicxray.com":[1,3],"musiczum.com":[1],"musik-media-shop.de":[1,9],"musik-produktiv.ch":[1,9],"musik-produktiv.de":[1,9],"musik-sammler.de":[1,12,3],"musikding.de":[1,9],"musiker-board.de":[1,12],"musiker-in-deiner-stadt.de":[12],"musiker-sucht-musiker.de":[1,12,3],"musikia.com":[1,9],"musikmac.com":[1,3],"musikverein.at":[1,12,3],"musikzoo.com":[1],"musimundo.com":[3,9],"musin.de":[12],"musinsa.com":[1,3,9],"musix.ch":[1,9],"musixmatch.com":[12,3],"muskegoncc.edu":[12],"muskelmacher-shop.de":[9],"muslima.com":[10],"muslimface.com":[1,12],"muslims4marriage.com":[10],"muslimshop.fr":[1,12],"musopen.org":[1,12],"muspy.com":[1,12,3],"mustakbil.com":[1,6],"mustang.org":[1,12],"mustang6g.com":[1,12],"mustangforums.com":[1,9,12],"mustangsunlimited.com":[9,12],"mustaphafersaoui.fr":[1,12,5]}