{"xspeeds.com":[12],"xspeeds.eu":[12],"xsph.ru":[12],"xsplit.com":[1,5,3],"xspo.de":[9],"xsportfitness.com":[1],"xsrv.jp":[12],"xstockvideo.com":[12,3,10],"xstory-fr.com":[12,3],"xsubs.tv":[12],"xsusenet.com":[1,5],"xsyon.com":[1,3],"xt-commerce.com":[1,9],"xtb.com":[1,2],"xtec.cat":[12],"xtechcommerce.com":[1],"xtend-life.com":[1,12,9],"xtenfaucet.com":[12],"xtensio.com":[1,5],"xtento.com":[1,5],"xtf.com":[1],"xtgem.com":[1,5],"xthor.bz":[1],"xthor.to":[1],"xtime.com":[1],"xtip.de":[1,3],"xtm-cloud.com":[12],"xtmmo.net":[12],"xtonight.com":[10],"xtool.ru":[1,12,5],"xtra.co.nz":[1],"xtra.no":[1,12],"xtrade.com":[1,2],"xtrader.co.uk":[12,9],"xtraframe.tv":[12],"xtragfx.com":[1],"xtralife.es":[3,9],"xtramath.org":[12],"xtranormal.com":[3],"xtravirt.com":[1,5],"xtrawine.com":[12,9],"xtream-codes.com":[1,5],"xtream-editor.com":[1,5],"xtreamer.net":[12],"xtreampanel.com":[1],"xtreemhost.com":[1,5],"xtremboy.com":[12],"xtremebuilder.net":[1],"xtremebullets.com":[1,9],"xtremediesel.com":[9,12],"xtremeguard.com":[5,9],"xtremespeeds.net":[12],"xtremesurf.info":[1],"xtremesystems.org":[10],"xtremetv.org":[12],"xtremevbtalk.com":[5,10],"xtremewarehouse.com.au":[9],"xtremewrestlingtorrents.net":[1],"xtremmedia.com":[9],"xtrend-alliance.com":[10],"xtrend-home.de":[10],"xtrf.eu":[1],"xtrons.co.uk":[9,12],"xtube.com":[12],"xtwostore.fr":[1,9],"xucker.de":[1,9],"xueqiu.com":[1,12],"xuetangx.com":[12],"xuite.net":[1,3,3],"xungde.vn":[12],"xunitytalk.com":[1],"xunlei.com":[1,5],"xunta.es":[1,12],"xunta.gal":[1,12],"xunyou.com":[1,12,3],"xusenet.com":[5,9],"xviata.com":[12],"xvideos.com":[12],"xvideoslive.com":[12],"xvoucher.com":[1,12],"xvpn.io":[5,12],"xwatchseries.to":[3],"xwiki.com":[1,5],"xwis.net":[12],"xwt-classics.net":[1],"xxcycle.com":[9],"xxcycle.fr":[9],"xxe.fr":[1],"xxl-deals.de":[9],"xxl.dk":[9],"xxl.fi":[1,9],"xxl.no":[1,9],"xxl.se":[1,9],"xxlnutrition.com":[12],"xxtorrent.net":[12,1],"xxx-gay-games.com":[12,3],"xxxaddressbook.com":[1],"xxxblackbook.com":[10],"xxxbunker.com":[12]}