{"galleyfoods.com":[1,3],"gallifreybase.com":[1,12],"gallito.com.uy":[1,9,12],"gallo.com":[12,1],"galloarts.org":[1,12,3],"gallowayprecision.com":[9,12],"galls.com":[9],"gallup.com":[1,12],"gallupforum.fi":[1,12],"galluppanelet.no":[1,12],"gallupstrengthscenter.com":[1,12],"galottery.com":[1,3],"galpenergia.com":[1],"galuoc.net":[12],"galvanize.com":[1,12],"galvnews.com":[12],"gam.org":[1,3],"gama-gama.ru":[12],"gamai.ru":[12],"gamaliel.com":[9,12],"gamaplay.net":[1,12,3],"gamasutra.com":[1,12,3],"gamatotv.me":[1,3],"gamazavr.ru":[1,3,9],"gambacicli.com":[9],"gamberorosso.it":[1,12,3],"gambettesbox.fr":[1],"gambio-support.de":[1],"gambit.com":[3],"gambling-affiliation.com":[1],"gamcore.com":[12,3],"game-card.net":[3],"game-club-arte.com":[12],"game-connection.com":[1,12,3],"game-debate.com":[12,3,5],"game-guide.fr":[12,3,3],"game-host.org":[1,5],"game-insight.com":[1,3],"game-labs.net":[12],"game-leap.com":[1,12],"game-message-portal.com":[1,5],"game-oldies.com":[3],"game-on.no":[9,12],"game-pal.com":[1,12,3],"game-ready.com":[12],"game-state.com":[1,12,3],"game-tuts.com":[10],"game.co.uk":[3,9],"game.es":[3],"game.fr":[3,3,7],"game.net":[3,9],"game2.cn":[1,3,9],"game2dl.net":[9],"game321.com":[1],"game7.com.br":[9],"game735.com":[12,3,3],"game8.vn":[1,12,3],"gameaccess.ca":[3],"gameagent.com":[3],"gameanalytics.com":[1],"gameanarchy.net":[12],"gamearena.com.au":[1,12],"gameassists.co.uk":[12],"gamebai.net":[1,3],"gamebanana.com":[3],"gamebank.vn":[1,9],"gamebase.com.tw":[3,3],"gamebatte.com":[3],"gamebattles.com":[1,3],"gamebench.net":[1,5],"gamebillet.com":[9],"gameblog.fr":[3,3,7],"gamebomb.ru":[3,3],"gamebookers.com":[3,3],"gamebox.com":[3],"gamebundle.com":[12,3],"gamecard.mobi":[3,9],"gamecarddelivery.com":[1,9],"gamecards.eu":[3],"gamecash.fr":[3,7,9],"gamechanger.com":[1,12],"gamechanger.io":[1,12],"gamecheap.com":[1],"gamecheap.net":[1],"gameclient.eu":[12],"gameclub.com":[12],"gameclub.ph":[12],"gamecodeshop.de":[3,9],"gamecodeur.fr":[1,12],"gamecoins.com":[12],"gamecolony.com":[3],"gamecom.jp":[1,12],"gamecp.com":[1,5],"gamecreate.com":[1,5],"gamecredits.com":[1],"gamed.de":[1,5],"gamedesire.com":[3],"gamedev.net":[1,12,5],"gamedev.tv":[12]}