{"moneydj.com":[1,2,12],"moneydoc.fr":[1],"moneyextra.com":[1,2],"moneyfarm.com":[1,2],"moneyforward.com":[1],"moneygram.co.uk":[1],"moneygram.com":[1,9],"moneygram.de":[12],"moneyguidepro.com":[1,12],"moneyhouse.ch":[1],"moneyhouse.de":[1,12,3],"moneyinstructor.com":[1,12],"moneyjobs.com":[1,6],"moneykey.com":[1,2],"moneykit.net":[1,2],"moneylife.in":[1,12],"moneylion.com":[1,2],"moneylook.jp":[1,12],"moneylover.me":[1],"moneymail.cz":[1],"moneymakerdiscussion.com":[1],"moneymakergroup.com":[1,12],"moneymakingforextools.com":[2],"moneyman.es":[1],"moneyman.ru":[1,2],"moneymanagement.org":[1,2,12],"moneymappress.com":[1,12],"moneymarket.com.au":[1,2],"moneymarketing.co.uk":[1,2],"moneymart.ca":[1,2],"moneymasterthegame.com":[1,12],"moneyme.com.au":[1,2],"moneymeets.com":[1,2],"moneymetals.com":[1,2,9],"moneymiljonair.nl":[1,9],"moneymillionar.de":[1,9],"moneymillionnaire.fr":[1,9],"moneymonk.nl":[1],"moneymorning.com":[1,2,7],"moneynetwork.com":[1],"moneynetworkedu.com":[12],"moneyone.com.au":[1],"moneyonlineinvestment.com":[1,2],"moneyou.at":[1],"moneyou.be":[1,2,9],"moneyou.de":[1,2],"moneyou.nl":[1,2],"moneypartners.co.jp":[1,2],"moneypenny.com":[1],"moneyplatform.biz":[1],"moneypolo.com":[1],"moneypot.com":[7],"moneysavingexpert.com":[1,2],"moneysense.ca":[1,2],"moneysharp.org":[1,12],"moneyshow.com":[1,2,12],"moneyskill.org":[1,12],"moneysmart.gov.au":[1,2],"moneysoft.com.au":[1],"moneystorm.com":[3,3],"moneystream.com":[1],"moneysupermarket.com":[1,2],"moneytalk-ondemand.com":[1],"moneytalksnews.com":[9],"moneything.com":[1,2],"moneytips.com":[1,2],"moneytrackin.com":[1,12],"moneytree.jp":[1],"moneytreeinc.com":[1,2],"moneyveo.ua":[1,2],"moneyweb.co.za":[1,2,7],"moneyweek.com":[1,2],"moneyweekresearch.com":[1,12],"moneywizapp.com":[1],"moneza.ru":[1],"monfairepart.com":[1,9],"monfax.com":[1],"monfinancier.com":[1,2,12],"monflo.com":[5],"mongars.fr":[10],"mongeralaegon.com.br":[1],"mongodb.com":[1],"mongodb.org":[1],"mongohouse.com":[1],"mongohq.com":[5,3],"mongolab.com":[1,5],"mongoosemetrics.com":[1],"monguidesante.com":[12],"monicahq.com":[1,12],"monicavinader.com":[1,9],"moniker.com":[12],"monin.com":[12,1,3],"monipass.com":[12],"monipla.com":[1,12,9],"moniteurautomobile.be":[1,12],"monitis.com":[1],"monitor.net.ru":[12,5,9],"monitor.us":[1,5],"monitorank.com":[1,5]}