{"homesandantiques.com":[1,12],"homesandland.com":[8],"homesavings.com":[1,2],"homesbymarco.com":[1,8],"homescan.ca":[1],"homescan.com":[12],"homeschool-life.com":[1,12],"homeschool-planner.com":[12],"homeschoolbuyersco-op.org":[1,12,9],"homeschoolskedtrack.com":[1,12],"homesciencetools.com":[12,9],"homesconnect.com":[1,8],"homescouting.com":[1],"homescreen.me":[12],"homesearch.com":[1,8],"homesecuritystore.com":[9],"homeseer.com":[1],"homeserve.fr":[1],"homeserver.com":[12],"homeserverland.com":[12],"homeservershow.com":[12,3,5],"homeserveusa.com":[1],"homeservice24.ch":[1,6],"homesew.com":[9],"homeshop18.com":[9],"homeshopmachinist.net":[1,12,9],"homeshopping.pk":[9],"homesite.com":[1,2],"homesmartagent.com":[12],"homesnap.com":[12],"homespun.com":[3],"homespyvideo.com":[12],"homestars.com":[1],"homestatehealth.com":[1,12,4],"homestay.com":[1,11],"homestaynetwork.org":[1,12],"homestead.com":[1],"homesteadingtoday.com":[10],"homesteps.com":[1,8],"homestepsconnect.com":[1],"homestreet.com":[1,2],"homestyler.com":[1],"homesuccesspro.com":[1],"homeswapper.co.uk":[1],"hometalk.com":[1,12,9],"hometeamsonline.com":[1,3],"hometesterclub.com":[1,12],"hometheater.co.il":[1,5,9],"hometheaterforum.com":[3,9],"hometheatershack.com":[3],"hometownhealth.com":[1],"hometownpass.com":[1,11],"hometrainingtools.com":[12,9],"hometrust.ca":[1,2],"hometrustbanking.com":[1,2],"homeunion.com":[1,2],"homewarranty.com":[1],"homewav.com":[1],"homewetbar.com":[12,9],"homewisedocs.com":[1],"homewizard.com":[1],"homewizard.nl":[1,12,9],"homeworkersnet.com":[1,5,6],"homeworkmarket.com":[12],"homeworkoutrevolution.com":[1,12],"homeworksolutions.com":[1],"homezada.com":[1],"homfurniture.com":[1,9],"homido.com":[1],"homify.de":[1,9],"homify.fr":[1,9],"homileticsonline.com":[1,12],"homingpin.com":[1,12],"hommefort.fr":[9],"hommell-magazines.com":[1,9],"hommell.com":[9],"homo.nl":[12],"homoeopathiefuchs.de":[1,12,9],"homunity.com":[12,10,11],"hon.com":[1,9],"hon.org":[1,12],"hon3yhd.com":[1],"honcho.com.au":[1],"honda-assurance.fr":[1],"honda-board.de":[12],"honda-eu.com":[1,12],"honda-tech.com":[12],"honda.ca":[1,9,12],"honda.co.jp":[1,9,12],"honda.com":[1,12],"hondaautomotiveparts.com":[9,12],"hondafcu.org":[1,2],"hondafinancialservices.com":[1],"hondahookup.com":[1,12],"hondapartsdeals.com":[9,12],"hondapartsnow.com":[9,12],"hondashadow.net":[1,3,9],"hondaweb.com":[12],"hondros.com":[1,12]}