{"nike.com":[12],"nike.com.br":[9],"nike.com.hk":[9],"nike.net":[10],"nike.sk":[1,12,3],"nikecdn.com":[12],"nikeplus.com":[9],"nikestore.com.au":[12],"niketalk.com":[10],"nikita.no":[1,9],"nikkan-gendai.com":[12],"nikkan.co.jp":[1,12],"nikkei-r.co.jp":[1,12,3],"nikkei.co.jp":[1,12],"nikkei.com":[1,12],"nikkeibp.co.jp":[1,12],"nikken.com":[1],"nikkisushi.com":[1],"nikon-asia.com":[1,12],"nikon-fotografie.de":[1,12,3],"nikon-image.com":[1,12],"nikon-photocontest.com":[1,12,3],"nikon.ca":[1,9],"nikon.ch":[1,12,9],"nikon.co.uk":[1,9],"nikon.com":[1],"nikon.de":[1,9],"nikon.fr":[1,9],"nikoncafe.com":[1,12,3],"nikonclub.fr":[1],"nikonclub.it":[1,12],"nikonclubitalia.com":[1,12],"nikondealernet.com":[1],"nikonians.org":[1,12],"nikonimagespace.com":[1,10],"nikonimgsupport.com":[1],"nikonistas.com":[1,12],"nikonisti.ro":[1,12],"nikonites.com":[3,10],"nikonpassion.com":[1],"nikonpro.com":[1,9],"nikonpro.fr":[1,12],"nikonrepair.eu":[12],"nikonschool.in":[1,12],"nikonsso.com":[12],"nikonusa.com":[9],"niksoftware.com":[1],"nikwax.co.uk":[1,9],"nikwax.com":[1,9],"nil.com":[1,5],"nile.com.my":[9],"nilecorp.com":[9],"nilemotors.net":[1,9,12],"nilfisk-conso.fr":[1,9],"nili.ca":[1],"niloo.fr":[1,5],"nilufer.com.tr":[1,12],"nimans.net":[1,5,9],"nimaxtheatres.com":[1,12,3],"nimber.com":[1,9],"nimbi.com.br":[1],"nimbit.com":[1],"nimble.com":[1],"nimble.com.au":[1,2],"nimbledeals.com":[1],"nimblerx.com":[1,9],"nimbleschedule.com":[1],"nimblestorage.com":[1,5],"nimbox.co.uk":[1,5],"nimbuzz.com":[1,10],"nimbuzzout.com":[1],"nimc.gov.ng":[1,5],"nimenhuuto.com":[1,3,3],"nimes.fr":[1,12],"nimfomane.com":[12],"nimsoft.com":[1],"nin-nin-game.com":[9],"nin.com":[3],"ninaricci.com":[9],"ninasushi.com":[1],"nine-mine.com":[1,5],"nine.ch":[1,5],"nine.com.au":[3,7],"ninecircles.co.uk":[9],"ninefold.com":[1],"ninelineapparel.com":[9],"ninemsn.com.au":[12],"ninenrol.gov.ng":[12],"ninerewards.com.au":[1],"ninesharp.co.uk":[1],"ninety9lives.com":[3],"ninewest.com":[9],"ning.com":[1,12],"ninite.com":[1,5],"ninja-squad.com":[1],"ninja.co.jp":[1],"ninjabet.it":[1,3],"ninjacademy.it":[1,12],"ninjacloak.com":[12]}